pymdcord/__init__.py
pymdcord/classes.py
pymdcord/main.py
pymdcord-0.5.3.dist-info/METADATA
pymdcord-0.5.3.dist-info/WHEEL
pymdcord-0.5.3.dist-info/RECORD
