Metadata-Version: 2.1
Name: pymdcord
Version: 0.5.3
Summary: A markdown parser for discord markdown syntax
Author: Shinwoo PARK
Author-email: shinwoo.park@psw.kr
Requires-Python: >=3.10,<4.0
Classifier: Programming Language :: Python :: 3
Classifier: Programming Language :: Python :: 3.10
Classifier: Programming Language :: Python :: 3.11
